stko/__init__.py
stko/_version.py
stko/functional_groups.py
stko/molecular_utilities.py
stko/molecule_analysis.py
stko/py.typed
stko/topology_functions.py
stko/_internal/__init__.py
stko/_internal/internal_types.py
stko/_internal/calculators/__init__.py
stko/_internal/calculators/open_babel_calculators.py
stko/_internal/calculators/openmm_calculators.py
stko/_internal/calculators/orca_calculators.py
stko/_internal/calculators/planarity_calculators.py
stko/_internal/calculators/rdkit_calculators.py
stko/_internal/calculators/rmsd_calculators.py
stko/_internal/calculators/shape_calculators.py
stko/_internal/calculators/torsion_calculators.py
stko/_internal/calculators/utilities.py
stko/_internal/calculators/xtb_calculators.py
stko/_internal/calculators/extractors/__init__.py
stko/_internal/calculators/extractors/orca_extractor.py
stko/_internal/calculators/extractors/utilities.py
stko/_internal/calculators/extractors/xtb_extractor.py
stko/_internal/calculators/geometry_analysis/__init__.py
stko/_internal/calculators/geometry_analysis/geometry.py
stko/_internal/calculators/results/__init__.py
stko/_internal/calculators/results/energy_results.py
stko/_internal/calculators/results/orca_results.py
stko/_internal/calculators/results/planarity_results.py
stko/_internal/calculators/results/rmsd_results.py
stko/_internal/calculators/results/shape_results.py
stko/_internal/calculators/results/torsion_results.py
stko/_internal/calculators/results/xtb_results.py
stko/_internal/molecular/__init__.py
stko/_internal/molecular/molecular_utilities.py
stko/_internal/molecular/atoms/__init__.py
stko/_internal/molecular/atoms/dummy_atom.py
stko/_internal/molecular/atoms/positioned_atom.py
stko/_internal/molecular/constructed/__init__.py
stko/_internal/molecular/constructed/constructed_analysis.py
stko/_internal/molecular/conversion/__init__.py
stko/_internal/molecular/conversion/md_analysis.py
stko/_internal/molecular/conversion/z_matrix.py
stko-2025.12.7.1.dist-info/licenses/LICENSE
stko-2025.12.7.1.dist-info/METADATA
stko-2025.12.7.1.dist-info/WHEEL
stko-2025.12.7.1.dist-info/top_level.txt
stko-2025.12.7.1.dist-info/RECORD
