Metadata-Version: 2.4
Name: stko
Version: 2025.12.7.1
Maintainer-email: Andrew Tarzia <andrew.tarzia@gmail.com>, Lukas Turcani <lukasturcani93@gmail.com>
Project-URL: github, https://github.com/JelfsMaterialsGroup/stko
Project-URL: documentation, https://stko-docs.readthedocs.io
Requires-Python: >=3.11
License-File: LICENSE
Requires-Dist: numpy
Requires-Dist: stk
Requires-Dist: networkx
Requires-Dist: rmsd
Requires-Dist: mdanalysis
Requires-Dist: openmm
Provides-Extra: dev
Requires-Dist: ruff; extra == "dev"
Requires-Dist: mypy; extra == "dev"
Requires-Dist: moldoc; extra == "dev"
Requires-Dist: pytest<8; extra == "dev"
Requires-Dist: pytest-datadir; extra == "dev"
Requires-Dist: pytest-lazy-fixture; extra == "dev"
Requires-Dist: pytest-cov; extra == "dev"
Requires-Dist: sphinx; extra == "dev"
Requires-Dist: sphinx-copybutton; extra == "dev"
Requires-Dist: sphinx-rtd-theme>0.5.1; extra == "dev"
Requires-Dist: twine; extra == "dev"
Requires-Dist: build; extra == "dev"
Provides-Extra: cuda
Requires-Dist: torch>=2.8.0; extra == "cuda"
Requires-Dist: OpenMM-CUDA-12; extra == "cuda"
Dynamic: license-file
